evalify/__init__.py
evalify/evalify.py
evalify/metrics.py
evalify/utils.py
evalify-1.0.0.dist-info/AUTHORS.md
evalify-1.0.0.dist-info/LICENSE
evalify-1.0.0.dist-info/METADATA
evalify-1.0.0.dist-info/WHEEL
evalify-1.0.0.dist-info/RECORD
