Metadata-Version: 2.1
Name: evalify
Version: 1.0.0
Summary: Evaluate your face or voice verification models literally in seconds.
Home-page: https://github.com/ma7555/evalify
License: BSD-3-Clause
Keywords: biometric verification,biometric authentication,evaluation
Author: Mahmoud Bahaa
Author-email: evalify@ma7555.anonaddy.com
Requires-Python: >=3.9,<4.0
Classifier: Development Status :: 4 - Beta
Classifier: Intended Audience :: Developers
Classifier: License :: OSI Approved :: BSD License
Classifier: Natural Language :: English
Classifier: Programming Language :: Python :: 3
Classifier: Programming Language :: Python :: 3.9
Classifier: Programming Language :: Python :: 3.10
Classifier: Programming Language :: Python :: 3.11
Classifier: Programming Language :: Python :: 3.12
Classifier: Programming Language :: Python :: 3.13
Provides-Extra: dev
Provides-Extra: doc
Provides-Extra: test
Requires-Dist: mkdocs (>=1.4.0) ; extra == "doc"
Requires-Dist: mkdocs-include-markdown-plugin (>=6.0.0) ; extra == "doc"
Requires-Dist: mkdocs-material (>=9.2.0,<10.0.0) ; extra == "doc"
Requires-Dist: mkdocstrings (>=0.26.0) ; extra == "doc"
Requires-Dist: mkdocstrings-python (>=1.12.2) ; extra == "doc"
Requires-Dist: numpy (>=2.0.0,<3.0.0)
Requires-Dist: pandas (>=2.0.0,<3.0.0)
Requires-Dist: pip (>=23.2.0) ; extra == "dev"
Requires-Dist: poetry (>=1.8.0,<2.0.0) ; extra == "dev"
Requires-Dist: psutil (>=5.9.0,<6.0.0)
Requires-Dist: pyreadline3 (>=3.4.1,<4.0.0) ; extra == "test"
Requires-Dist: pytest (>=7.2.0,<8.0.0) ; extra == "test"
Requires-Dist: pytest-cov (>=4.0.0,<5.0.0) ; extra == "test"
Requires-Dist: ruff (>=0.7.2) ; extra == "test"
Requires-Dist: scikit-learn (>=1.2.0,<2.0.0)
Requires-Dist: scipy (>=1.10.0) ; extra == "test"
Requires-Dist: toml (>0.8.0) ; extra == "dev"
Requires-Dist: tox (>=4.7.0,<5.0.0) ; extra == "dev"
Requires-Dist: twine (>=5.0.0,<6.0.0) ; extra == "dev"
Requires-Dist: virtualenv (>=20.24.0) ; extra == "dev"
